{
    "IsActive": true,
    "IsOmniScriptEmbeddable": false,
    "Name": "DetermineEligibility",
    "OmniProcessId": {
        "Name": "Check Eligibility and Assign Benefit",
        "VlocityDataPackType": "VlocityMatchingKeyObject",
        "VlocityMatchingRecordSourceKey": "OmniProcess/BenefitManagement/CheckEligibilityAndAssignBenefit/English",
        "VlocityRecordSObjectType": "OmniProcess"
    },
    "PropertySetConfig": {
        "HTMLTemplateId": "",
        "businessCategory": "",
        "businessEvent": "",
        "controlWidth": 12,
        "enableActionMessage": false,
        "enableDefaultAbort": false,
        "errorMessage": {
            "custom": [
            ],
            "default": ""
        },
        "extraPayload": {
        },
        "failureAbortLabel": "Abort",
        "failureAbortMessage": "Are you sure?",
        "failureGoBackLabel": "Go Back",
        "failureNextLabel": "",
        "inProgressMessage": "In Progress",
        "integrationProcedureKey": "BenefitManagement_DetermineEligibleBenefitAmount",
        "label": "DetermineEligibility",
        "message": {
        },
        "postMessage": "Done",
        "postTransformBundle": "",
        "preTransformBundle": "",
        "pubsub": false,
        "redirectNextLabel": "Next",
        "redirectNextWidth": 3,
        "redirectPageName": "",
        "redirectPreviousLabel": "Previous",
        "redirectPreviousWidth": 3,
        "redirectTemplateUrl": "vlcAcknowledge.html",
        "remoteOptions": {
            "chainable": false,
            "postTransformBundle": "",
            "preTransformBundle": "",
            "useFuture": false
        },
        "remoteTimeout": 30000,
        "responseJSONNode": "",
        "responseJSONPath": "",
        "sendJSONNode": "",
        "sendJSONPath": "",
        "show": {
            "group": {
                "operator": "AND",
                "rules": [
                    {
                        "condition": "=",
                        "data": "false",
                        "field": "IAStatus:IsBAPresent"
                    },
                    {
                        "group": {
                            "operator": "OR",
                            "rules": [
                                {
                                    "condition": "=",
                                    "data": "In Review",
                                    "field": "IAStatus:Status"
                                },
                                {
                                    "condition": "=",
                                    "data": "Application Accepted",
                                    "field": "IAStatus:Status"
                                }
                            ]
                        }
                    }
                ]
            }
        },
        "showPersistentComponent": [
            true,
            false
        ],
        "ssm": false,
        "svgIcon": "",
        "svgSprite": "",
        "useContinuation": false,
        "validationRequired": "Step",
        "wpm": false
    },
    "Type": "Integration Procedure Action",
    "VlocityDataPackType": "SObject",
    "VlocityRecordSObjectType": "OmniProcessElement",
    "VlocityRecordSourceKey": "OmniProcessElement/OmniProcess/BenefitManagement/CheckEligibilityAndAssignBenefit/English/DetermineEligibility"
}