{
    "IsActive": true,
    "IsOmniScriptEmbeddable": false,
    "Name": "EditMessage",
    "OmniProcessId": {
        "Name": "Business License Application",
        "VlocityDataPackType": "VlocityMatchingKeyObject",
        "VlocityMatchingRecordSourceKey": "OmniProcess/LicensingAndPermitting/BusinessLicenseApplication/English",
        "VlocityRecordSObjectType": "OmniProcess"
    },
    "ParentElementId": {
        "Name": "ApplicationInformation",
        "OmniProcessId": {
            "Name": "Business License Application",
            "VlocityDataPackType": "VlocityMatchingKeyObject",
            "VlocityMatchingRecordSourceKey": "OmniProcess/LicensingAndPermitting/BusinessLicenseApplication/English",
            "VlocityRecordSObjectType": "OmniProcess"
        },
        "VlocityDataPackType": "VlocityMatchingKeyObject",
        "VlocityMatchingRecordSourceKey": "OmniProcessElement/OmniProcess/LicensingAndPermitting/BusinessLicenseApplication/English/ApplicationInformation",
        "VlocityRecordSObjectType": "OmniProcessElement"
    },
    "ParentElementName": "ApplicationInformation",
    "ParentElementType": "Step",
    "PropertySetConfig": {
        "HTMLTemplateId": "",
        "controlWidth": 12,
        "dataJSON": false,
        "disOnTplt": false,
        "label": null,
        "sanitize": false,
        "show": {
            "group": {
                "operator": "AND",
                "rules": [
                    {
                        "condition": "=",
                        "data": "false",
                        "field": "isEditable"
                    }
                ]
            }
        },
        "text": "<p><strong><span style=\"color: #008000;\">You can't edit your application at this stage of the review process.</span></strong></p>",
        "textKey": ""
    },
    "Type": "Text Block",
    "VlocityDataPackType": "SObject",
    "VlocityRecordSObjectType": "OmniProcessElement",
    "VlocityRecordSourceKey": "OmniProcessElement/OmniProcess/LicensingAndPermitting/BusinessLicenseApplication/English/EditMessage"
}